TidyDistribution/README.md
TidyDistribution/TidyDistribution.py
TidyDistribution/TidyProbability.py
TidyDistribution/TidyQuantile.py
TidyDistribution/TidyRandom.py
TidyDistribution/TidySample.py
TidyDistribution/__init__.py
TidyDistribution/test/Starttest.py
TidyDistribution/test/renumberid.py
TidyDistribution/test/testTidyDistribution.txt
TidyDistribution/test/testTidyProbability.txt
TidyDistribution/test/testTidyQuantile.txt
TidyDistribution/test/testTidyRandom.txt
TidyDistribution/test/testTidySample.txt
tidydistribution-0.0.1.dist-info/METADATA
tidydistribution-0.0.1.dist-info/WHEEL
tidydistribution-0.0.1.dist-info/licenses/LICENSE
tidydistribution-0.0.1.dist-info/RECORD
