Metadata-Version: 2.1
Name: TidyDistribution
Version: 0.0.1
Summary: 使用Scipy库实现统计分布的简洁程序库，五个函数搞定所有常用的统计分布！
Project-URL: Homepage, https://github.com/LiuAndy-art/TidyDistribution
Project-URL: Documentation, https://github.com/LiuAndy-art/TidyDistribution
Project-URL: Repository, https://github.com/LiuAndy-art/TidyDistribution
Author-email: LiuAndy <andylau_dh@163.com>
Maintainer-email: LiuAndy <andylau_dh@163.com>
License: MIT License
License-File: LICENSE
Keywords: Scipy,函数封装,简介代码,统计分布
Classifier: License :: OSI Approved :: MIT License
Classifier: Operating System :: OS Independent
Classifier: Programming Language :: Python :: 3
Requires-Python: >=3.8
Requires-Dist: matplotlib
Requires-Dist: numpy
Requires-Dist: openpyxl
Requires-Dist: pandas
Requires-Dist: scipy
Requires-Dist: seaborn
Requires-Dist: statsmodels
Requires-Dist: xlrd
Requires-Dist: xlwt
